{
  "phase": "phase1",
  "startTime": "2025-06-22T20:56:47.534Z",
  "totalProducts": 4,
  "successful": [
    {
      "success": true,
      "productKey": "poximix-interior-05kg-poxipol",
      "originalUrl": "https://http2.mlstatic.com/resources/frontend/statics/img-not-available/1.1.0/F@2x.gif",
      "localFiles": {
        "preview": "poximix-interior-05kg-poxipol.jpg",
        "thumbnail": "poximix-interior-sm-poxipol.jpg"
      },
      "sizeKB": 51,
      "source": "MercadoLibre",
      "attemptedUrls": 2,
      "totalUrls": 3
    },
    {
      "success": true,
      "productKey": "latex-interior-4l-plavicon",
      "originalUrl": "https://http2.mlstatic.com/resources/frontend/statics/img-not-available/1.1.0/F@2x.gif",
      "localFiles": {
        "preview": "latex-interior-4l-plavicon.jpg",
        "thumbnail": "latex-interior-sm-plavicon.jpg"
      },
      "sizeKB": 51,
      "source": "MercadoLibre",
      "attemptedUrls": 1,
      "totalUrls": 3
    },
    {
      "success": true,
      "productKey": "plavipint-techos-poliuretanico-10l-plavicon",
      "originalUrl": "https://http2.mlstatic.com/resources/frontend/statics/img-not-available/1.1.0/F@2x.gif",
      "localFiles": {
        "preview": "plavipint-techos-poliuretanico-10l-plavicon.jpg",
        "thumbnail": "plavipint-techos-poliuretanico-sm-plavicon.jpg"
      },
      "sizeKB": 51,
      "source": "MercadoLibre",
      "attemptedUrls": 1,
      "totalUrls": 3
    },
    {
      "success": true,
      "productKey": "pincel-persianero-n20-galgo",
      "originalUrl": "https://http2.mlstatic.com/resources/frontend/statics/img-not-available/1.1.0/F@2x.gif",
      "localFiles": {
        "preview": "pincel-persianero-n20-galgo.jpg",
        "thumbnail": "pincel-persianero-sm-galgo.jpg"
      },
      "sizeKB": 51,
      "source": "MercadoLibre",
      "attemptedUrls": 1,
      "totalUrls": 3
    }
  ],
  "failed": [],
  "skipped": [],
  "endTime": "2025-06-22T20:57:24.275Z",
  "duration": 36741,
  "successRate": 1
}